datacleanx/__init__.py
datacleanx/ai_suggestions.py
datacleanx/cleaning.py
datacleanx/utils.py
datacleanx/validation.py
datacleanx/visualization.py
datascour-0.1.1.dist-info/licenses/LICENSE
datascour-0.1.1.dist-info/METADATA
datascour-0.1.1.dist-info/WHEEL
datascour-0.1.1.dist-info/top_level.txt
datascour-0.1.1.dist-info/RECORD
